{
  "name": "Network Connectivity Center",
  "width": 319,
  "height": 291.89940037147966,
  "elements": [
    {
      "type": "line",
      "id": "_cyMgOXAnGbg3Q",
      "fillStyle": "solid",
      "strokeWidth": 1,
      "strokeStyle": "solid",
      "roughness": 0,
      "opacity": 100,
      "angle": 0,
      "x": 162.02627528345715,
      "y": 23.175686866702563,
      "strokeColor": "#000000",
      "backgroundColor": "#aecbfa",
      "width": 15.362393708526417,
      "height": 30.68702407869921,
      "seed": 2034951543,
      "groupIds": [
        "YpuGDj1pXJUomQ",
        "3f83HsVzb_Cvng",
        "5yNehOcTKdz-wg"
      ],
      "strokeSharpness": "sharp",
      "boundElements": [],
      "lastCommittedPoint": null,
      "startArrowhead": null,
      "endArrowhead": null,
      "points": [
        [
          0,
          0
        ],
        [
          0,
          -30.687024078699213
        ],
        [
          0,
          -30.687024078699213
        ],
        [
          -1.5658723902085399,
          -30.607801561999956
        ],
        [
          -3.0876062944054556,
          -30.375255465746072
        ],
        [
          -4.55737273856186,
          -29.997072819730157
        ],
        [
          -5.967321589259565,
          -29.480939772103547
        ],
        [
          -7.309581553691131,
          -28.83454158937637
        ],
        [
          -8.576323657827654,
          -28.0655600114939
        ],
        [
          -9.759683661991449,
          -27.181686476454786
        ],
        [
          -10.851811432764341,
          -26.190600079280635
        ],
        [
          -11.844863889857917,
          -25.09999402125255
        ],
        [
          -12.73096974046473,
          -23.917545634109686
        ],
        [
          -13.502307063685635,
          -22.650946355850717
        ],
        [
          -14.15099751358343,
          -21.307878808062114
        ],
        [
          -14.669198009869701,
          -19.89602913889523
        ],
        [
          -15.049072525385789,
          -18.42308173321898
        ],
        [
          -15.282749767324246,
          -16.896724502467148
        ],
        [
          -15.362393708526417,
          -15.324638304943779
        ],
        [
          -15.282749767324246,
          -13.752978821770625
        ],
        [
          -15.049072525385789,
          -12.227820623077278
        ],
        [
          -14.669198009869701,
          -10.756735243656546
        ],
        [
          -14.15099751358343,
          -9.347297744866136
        ],
        [
          -13.502307063685635,
          -8.007086714628617
        ],
        [
          -12.73096974046473,
          -6.7436772143016945
        ],
        [
          -11.844863889857917,
          -5.564637252113318
        ],
        [
          -10.851811432764341,
          -4.477552469115793
        ],
        [
          -9.759683661991449,
          -3.489983820407332
        ],
        [
          -8.576323657827654,
          -2.6095204736051443
        ],
        [
          -7.309581553691131,
          -1.8437304369371468
        ],
        [
          -5.967321589259565,
          -1.200185245196188
        ],
        [
          -4.55737273856186,
          -0.6864670128697057
        ],
        [
          -3.0876062944054556,
          -0.31014727475052695
        ],
        [
          -1.5658723902085399,
          -0.07879756563147922
        ],
        [
          0,
          0
        ],
        [
          0,
          0
        ]
      ]
    },
    {
      "type": "line",
      "id": "ajuTLVcdwWeApg",
      "fillStyle": "solid",
      "strokeWidth": 1,
      "strokeStyle": "solid",
      "roughness": 0,
      "opacity": 100,
      "angle": 0,
      "x": 177.38866899198115,
      "y": 7.8133002113058865,
      "strokeColor": "#000000",
      "backgroundColor": "#679df6",
      "width": 15.324645358073528,
      "height": 30.68702407869921,
      "seed": 1096388985,
      "groupIds": [
        "XA3dvUERsyJ7zQ",
        "3f83HsVzb_Cvng",
        "5yNehOcTKdz-wg"
      ],
      "strokeSharpness": "sharp",
      "boundElements": [],
      "lastCommittedPoint": null,
      "startArrowhead": null,
      "endArrowhead": null,
      "points": [
        [
          0,
          0
        ],
        [
          0,
          0
        ],
        [
          -0.07922075341681634,
          -1.5654474391407476
        ],
        [
          -0.3117060164265517,
          -3.0860546058591822
        ],
        [
          -0.6897114525573578,
          -4.554135352003957
        ],
        [
          -1.2055068315969137,
          -5.962005292706144
        ],
        [
          -1.8513337108138668,
          -7.301976516531965
        ],
        [
          -2.6194759662554095,
          -8.566364638612498
        ],
        [
          -3.5021892614496952,
          -9.747483510796396
        ],
        [
          -4.491715153665384,
          -10.837650511497184
        ],
        [
          -5.580323412690147,
          -11.829177729281072
        ],
        [
          -6.760269702052149,
          -12.714379015996707
        ],
        [
          -8.023823791539064,
          -13.48557175005762
        ],
        [
          -9.363241344679054,
          -14.135066256747574
        ],
        [
          -10.770763918740773,
          -14.655181677762538
        ],
        [
          -12.238661283511894,
          -15.03823010166872
        ],
        [
          -13.75920320878009,
          -15.27652449867355
        ],
        [
          -15.324645358073528,
          -15.362382247190554
        ],
        [
          -15.324645358073528,
          15.324641831508655
        ],
        [
          -15.324645358073528,
          15.324641831508655
        ],
        [
          -13.75920320878009,
          15.245424604656714
        ],
        [
          -12.238661283511894,
          15.012946394776732
        ],
        [
          -10.770763918740773,
          14.634940958645926
        ],
        [
          -9.363241344679054,
          14.119145579606377
        ],
        [
          -8.023823791539064,
          13.473311647259662
        ],
        [
          -6.760269702052149,
          12.705165865253248
        ],
        [
          -5.580323412690147,
          11.82246314975359
        ],
        [
          -4.491715153665384,
          10.832937257537901
        ],
        [
          -3.5021892614496952,
          9.744325471948253
        ],
        [
          -2.6194759662554095,
          8.56437918258626
        ],
        [
          -1.8513337108138668,
          7.300825093099343
        ],
        [
          -1.2055068315969137,
          5.96141811965399
        ],
        [
          -0.6897114525573578,
          4.553892019027392
        ],
        [
          -0.3117060164265517,
          3.0859840745616385
        ],
        [
          -0.07922075341681634,
          1.5654421492934443
        ],
        [
          0,
          0
        ],
        [
          0,
          0
        ]
      ]
    },
    {
      "type": "line",
      "id": "dP24GHxTesohdw",
      "fillStyle": "solid",
      "strokeWidth": 1,
      "strokeStyle": "solid",
      "roughness": 0,
      "opacity": 100,
      "angle": 0,
      "x": 109.18268957092982,
      "y": 45.40774079322773,
      "strokeColor": "#000000",
      "backgroundColor": "#679df6",
      "width": 15.022669134145064,
      "height": 30.64928013645242,
      "seed": 1205673623,
      "groupIds": [
        "XA3dvUERsyJ7zQ",
        "3f83HsVzb_Cvng",
        "5yNehOcTKdz-wg"
      ],
      "strokeSharpness": "sharp",
      "boundElements": [],
      "lastCommittedPoint": null,
      "startArrowhead": null,
      "endArrowhead": null,
      "points": [
        [
          0,
          0
        ],
        [
          0,
          0
        ],
        [
          1.0274576240422277,
          -1.132732638776865
        ],
        [
          1.927965965610328,
          -2.3455253534114924
        ],
        [
          2.6984287007415144,
          -3.629977866364758
        ],
        [
          3.3357495054730055,
          -4.977682846967777
        ],
        [
          3.836839108971784,
          -6.380232964551681
        ],
        [
          4.198594134145285,
          -7.829227941577333
        ],
        [
          4.417911203900996,
          -9.31626750050561
        ],
        [
          4.491701047405877,
          -10.832937257537893
        ],
        [
          4.417911203900996,
          -12.351162229681318
        ],
        [
          4.198594134145285,
          -13.841954053639668
        ],
        [
          3.836839108971784,
          -15.295600569739257
        ],
        [
          3.3357495054730055,
          -16.702350826092715
        ],
        [
          2.6984287007415144,
          -18.052485609896603
        ],
        [
          1.927965965610328,
          -19.336271602087944
        ],
        [
          1.0274576240422277,
          -20.543979010168663
        ],
        [
          0,
          -21.66587098851091
        ],
        [
          -1.102721571666061,
          -22.66856154741575
        ],
        [
          -2.282413948356856,
          -23.551373586426617
        ],
        [
          -3.5311070934483606,
          -24.31122136127537
        ],
        [
          -4.840845076576065,
          -24.94500502143434
        ],
        [
          -6.2036649142457065,
          -25.449628242940754
        ],
        [
          -7.611596569833259,
          -25.821998228396698
        ],
        [
          -9.056687639539092,
          -26.05901160070964
        ],
        [
          -10.530968086739186,
          -26.157579089046543
        ],
        [
          -10.530968086739186,
          4.491701047405879
        ],
        [
          -10.530968086739186,
          4.491701047405879
        ],
        [
          -9.104680660962238,
          4.396229883031761
        ],
        [
          -7.691215825081283,
          4.1667351470384695
        ],
        [
          -6.299869604114426,
          3.8036611866006282
        ],
        [
          -4.939927443385141,
          3.3074382426333493
        ],
        [
          -3.6206818413466575,
          2.678517715440975
        ],
        [
          -2.3514217698873248,
          1.917343952198145
        ],
        [
          -1.1414291477657361,
          1.0243542469496987
        ],
        [
          0,
          0
        ],
        [
          0,
          0
        ]
      ]
    },
    {
      "type": "line",
      "id": "VSyf8ILKevkOPg",
      "fillStyle": "solid",
      "strokeWidth": 1,
      "strokeStyle": "solid",
      "roughness": 0,
      "opacity": 100,
      "angle": 0,
      "x": 98.31201101606825,
      "y": 49.8994418406337,
      "strokeColor": "#000000",
      "backgroundColor": "#aecbfa",
      "width": 15.626600422612729,
      "height": 30.64928013645242,
      "seed": 117111385,
      "groupIds": [
        "xMbpT92AZIZ0Fw",
        "3f83HsVzb_Cvng",
        "5yNehOcTKdz-wg"
      ],
      "strokeSharpness": "sharp",
      "boundElements": [],
      "lastCommittedPoint": null,
      "startArrowhead": null,
      "endArrowhead": null,
      "points": [
        [
          0,
          0
        ],
        [
          0.3019621176689533,
          0
        ],
        [
          0.3019621176689533,
          -30.64928013645242
        ],
        [
          0,
          -30.64928013645242
        ],
        [
          0,
          -30.64928013645242
        ],
        [
          -1.5290585794482965,
          -30.575483239817782
        ],
        [
          -3.024939236525441,
          -30.35615911693232
        ],
        [
          -4.479245220257187,
          -29.994411144888566
        ],
        [
          -5.883565673409785,
          -29.49332506795467
        ],
        [
          -7.229500318444106,
          -28.856004263223177
        ],
        [
          -8.508641824691278,
          -28.08553800152712
        ],
        [
          -9.712589914612167,
          -27.185029659959014
        ],
        [
          -10.832933730973021,
          -26.15757203591679
        ],
        [
          -11.849554221145507,
          -25.0248429237048
        ],
        [
          -12.744977256159693,
          -23.812050209070172
        ],
        [
          -13.51477699709384,
          -22.527597696116906
        ],
        [
          -14.154531131591073,
          -21.17989976864364
        ],
        [
          -14.659817347294528,
          -19.777346124494862
        ],
        [
          -15.026213331847336,
          -18.32835114746921
        ],
        [
          -15.249296772892627,
          -16.8413151151058
        ],
        [
          -15.324638304943775,
          -15.324638304943765
        ],
        [
          -15.250841408309139,
          -13.806416859365221
        ],
        [
          -15.031520811988555,
          -12.31562503540687
        ],
        [
          -14.669769313379922,
          -10.861982045872162
        ],
        [
          -14.168686763010907,
          -9.455228262953824
        ],
        [
          -13.531362431714536,
          -8.105089952585054
        ],
        [
          -12.760899696583348,
          -6.821307486958588
        ],
        [
          -11.860391355015249,
          -5.613600078877873
        ],
        [
          -10.832933730973021,
          -4.491701047405876
        ],
        [
          -9.672334176531102,
          -3.4425691556241595
        ],
        [
          -8.43433004958447,
          -2.53189020094824
        ],
        [
          -7.129977131025296,
          -1.7601014774229569
        ],
        [
          -5.770327675180875,
          -1.1276473322229599
        ],
        [
          -4.366451569202894,
          -0.6349650593930605
        ],
        [
          -2.9294010674186417,
          -0.28249900610790135
        ],
        [
          -1.4702284241554082,
          -0.07070057267184993
        ],
        [
          0,
          0
        ],
        [
          0,
          0
        ]
      ]
    },
    {
      "type": "line",
      "id": "js3tjwKrgvJYyw",
      "fillStyle": "solid",
      "strokeWidth": 1,
      "strokeStyle": "solid",
      "roughness": 0,
      "opacity": 100,
      "angle": 0,
      "x": 71.89021815980686,
      "y": 82.62471550344594,
      "strokeColor": "#000000",
      "backgroundColor": "#aecbfa",
      "width": 15.92856430356413,
      "height": 30.72475920453381,
      "seed": 906703799,
      "groupIds": [
        "xMbpT92AZIZ0Fw",
        "3f83HsVzb_Cvng",
        "5yNehOcTKdz-wg"
      ],
      "strokeSharpness": "sharp",
      "boundElements": [],
      "lastCommittedPoint": null,
      "startArrowhead": null,
      "endArrowhead": null,
      "points": [
        [
          0,
          0
        ],
        [
          0,
          0
        ],
        [
          -1.5658618105139084,
          0.07922780654657886
        ],
        [
          -3.0876027678405915,
          0.3117694945943582
        ],
        [
          -4.557369211996987,
          0.6899512589690588
        ],
        [
          -5.96731277284737,
          1.20608518823689
        ],
        [
          -7.309578027126257,
          1.8524833709640613
        ],
        [
          -8.576316604697904,
          2.621464948846537
        ],
        [
          -9.7596766088617,
          3.5053420104505273
        ],
        [
          -10.851804379634592,
          4.496426644342242
        ],
        [
          -11.844853310163288,
          5.587030939087889
        ],
        [
          -12.730966213899858,
          6.769474036383433
        ],
        [
          -13.502296483991007,
          8.036082131054597
        ],
        [
          -14.150991342094898,
          9.379153205408077
        ],
        [
          -14.66919712822849,
          10.790999348010082
        ],
        [
          -15.049066353897256,
          12.26393970055658
        ],
        [
          -15.282744477476935,
          13.790300457873284
        ],
        [
          -15.36238312883179,
          15.36239370852642
        ],
        [
          -15.283159730491308,
          16.928244939345685
        ],
        [
          -15.05061451587865,
          18.450000002931883
        ],
        [
          -14.672432751503948,
          19.91975939395852
        ],
        [
          -14.156298822236117,
          21.329694138396718
        ],
        [
          -13.509898876226508,
          22.671975262217547
        ],
        [
          -12.740919943267691,
          23.938703260094556
        ],
        [
          -11.857044644946138,
          25.122063264258355
        ],
        [
          -10.865960011054424,
          26.214198088161005
        ],
        [
          -9.775352189743899,
          27.20723643899507
        ],
        [
          -8.59290380260104,
          28.093363448991145
        ],
        [
          -7.326304524342069,
          28.86467961282278
        ],
        [
          -5.983236976553467,
          29.51338416898009
        ],
        [
          -4.571387307386582,
          30.03159171839611
        ],
        [
          -3.0984399017103286,
          30.41144507452293
        ],
        [
          -1.5720826709584994,
          30.64512936959115
        ],
        [
          0,
          30.72475920453381
        ],
        [
          0.5661811747323409,
          30.72475920453381
        ],
        [
          0.5661811747323409,
          0.07549670090577583
        ],
        [
          0.5661811747323409,
          0.07549670090577583
        ],
        [
          0.28309146900739,
          0.009430034483466212
        ],
        [
          0,
          0
        ],
        [
          0,
          0
        ]
      ]
    },
    {
      "type": "line",
      "id": "vpHHaKu8myYcag",
      "fillStyle": "solid",
      "strokeWidth": 1,
      "strokeStyle": "solid",
      "roughness": 0,
      "opacity": 100,
      "angle": 0,
      "x": 87.252604815204,
      "y": 97.94936086151938,
      "strokeColor": "#000000",
      "backgroundColor": "#679df6",
      "width": 14.796205480664316,
      "height": 30.64927660988755,
      "seed": 1782335289,
      "groupIds": [
        "Ho8XNuiNKIppxg",
        "3f83HsVzb_Cvng",
        "5yNehOcTKdz-wg"
      ],
      "strokeSharpness": "sharp",
      "boundElements": [],
      "lastCommittedPoint": null,
      "startArrowhead": null,
      "endArrowhead": null,
      "points": [
        [
          0,
          0
        ],
        [
          0,
          0
        ],
        [
          -0.07576824640137758,
          -1.5310299292150322
        ],
        [
          -0.29827685737157594,
          -3.0194166359266656
        ],
        [
          -0.6603422202543321,
          -4.457930662135249
        ],
        [
          -1.1547771958285402,
          -5.839335496711342
        ],
        [
          -1.7743840651784097,
          -7.15638052226603
        ],
        [
          -2.511989795342336,
          -8.40182922766988
        ],
        [
          -3.3603931408396743,
          -9.568423942404205
        ],
        [
          -4.312414015579048,
          -10.64892815533959
        ],
        [
          -5.360865280339331,
          -11.636105355346608
        ],
        [
          -6.498552742769629,
          -12.52271197816608
        ],
        [
          -7.718292790213692,
          -13.30149740640908
        ],
        [
          -9.012898283450387,
          -13.965218075816425
        ],
        [
          -10.37517855669371,
          -14.506637475258696
        ],
        [
          -11.797949997287404,
          -14.918512040476719
        ],
        [
          -13.274018412880586,
          -15.193591154081552
        ],
        [
          -14.796205480664316,
          -15.32464535807354
        ],
        [
          -14.796205480664316,
          15.324631251814012
        ],
        [
          -14.796205480664316,
          15.324631251814012
        ],
        [
          -13.280239273325176,
          15.199804961396381
        ],
        [
          -11.808787131157148,
          14.92934564778157
        ],
        [
          -10.389196652083305,
          14.520644990953645
        ],
        [
          -9.028820723874043,
          13.981136989675186
        ],
        [
          -7.735019287429502,
          13.318213323930252
        ],
        [
          -6.515138177390323,
          12.539293886221884
        ],
        [
          -5.376537334656655,
          11.651770356534168
        ],
        [
          -4.326569646998884,
          10.663076733629655
        ],
        [
          -3.372584475622528,
          9.580604697492412
        ],
        [
          -2.521941761427728,
          8.411774140625504
        ],
        [
          -1.7819873390551244,
          7.163976743012981
        ],
        [
          -1.1600846759697543,
          5.844632397157923
        ],
        [
          -0.6635760802473545,
          4.461160995563386
        ],
        [
          -0.29982501935296213,
          3.0209542182134186
        ],
        [
          -0.0761843810569669,
          1.5314319576111082
        ],
        [
          0,
          0
        ],
        [
          0,
          0
        ]
      ]
    },
    {
      "type": "line",
      "id": "5OkieBUFjZutRg",
      "fillStyle": "solid",
      "strokeWidth": 1,
      "strokeStyle": "solid",
      "roughness": 0,
      "opacity": 100,
      "angle": 0,
      "x": 87.78104292933085,
      "y": 150.83068081823785,
      "strokeColor": "#000000",
      "backgroundColor": "#aecbfa",
      "width": 15.173659009391736,
      "height": 30.68703906659994,
      "seed": 469345495,
      "groupIds": [
        "lW5C0dhNSpLkgg",
        "3f83HsVzb_Cvng",
        "5yNehOcTKdz-wg"
      ],
      "strokeSharpness": "sharp",
      "boundElements": [],
      "lastCommittedPoint": null,
      "startArrowhead": null,
      "endArrowhead": null,
      "points": [
        [
          0,
          0
        ],
        [
          0,
          0
        ],
        [
          -1.0274611506071034,
          1.13273263877687
        ],
        [
          -1.9279694921752033,
          2.3455183002817424
        ],
        [
          -2.6984322273063914,
          3.629977866364763
        ],
        [
          -3.335753032037885,
          4.977675793838026
        ],
        [
          -3.8368391089717786,
          6.380232964551684
        ],
        [
          -4.19859060758041,
          7.8292279415773365
        ],
        [
          -4.417914730465874,
          9.316267500505623
        ],
        [
          -4.4917081005356305,
          10.832930204408145
        ],
        [
          -4.417914730465874,
          12.351158703116452
        ],
        [
          -4.19859060758041,
          13.841950527074802
        ],
        [
          -3.8368391089717786,
          15.295600569739266
        ],
        [
          -3.335753032037885,
          16.702347299527847
        ],
        [
          -2.6984322273063914,
          18.052485609896618
        ],
        [
          -1.9279694921752033,
          19.336268075523076
        ],
        [
          -1.0274611506071034,
          20.54397548360379
        ],
        [
          0,
          21.665874515075803
        ],
        [
          1.1169512609483294,
          22.680946843266884
        ],
        [
          2.3113141475311276,
          23.57260350699149
        ],
        [
          3.5755629702989853,
          24.337769341676097
        ],
        [
          4.902186146062007,
          24.97331275770913
        ],
        [
          6.283650932241027,
          25.4761726967766
        ],
        [
          7.712449272211028,
          25.843231675526454
        ],
        [
          9.181051949957727,
          26.071400423125663
        ],
        [
          10.681950908856106,
          26.157589668741178
        ],
        [
          10.681950908856106,
          -4.529449397858761
        ],
        [
          10.681950908856106,
          -4.529449397858761
        ],
        [
          9.181051949957727,
          -4.4308043250945435
        ],
        [
          7.712449272211028,
          -4.193269021179678
        ],
        [
          6.283650932241027,
          -3.8195095691618466
        ],
        [
          4.902186146062007,
          -3.3121497333101946
        ],
        [
          3.5755629702989853,
          -2.673869702931916
        ],
        [
          2.3113141475311276,
          -1.907321454815182
        ],
        [
          1.1169512609483294,
          -1.0151428594886482
        ],
        [
          0,
          0
        ],
        [
          0,
          0
        ]
      ]
    },
    {
      "type": "line",
      "id": "BxZ2yOmZ1X22lg",
      "fillStyle": "solid",
      "strokeWidth": 1,
      "strokeStyle": "solid",
      "roughness": 0,
      "opacity": 100,
      "angle": 0,
      "x": 98.65172148419174,
      "y": 146.33897977083257,
      "strokeColor": "#000000",
      "backgroundColor": "#679df6",
      "width": 15.494488249157381,
      "height": 30.68702496034044,
      "seed": 1971386393,
      "groupIds": [
        "dw4no3UtBSH2QQ",
        "3f83HsVzb_Cvng",
        "5yNehOcTKdz-wg"
      ],
      "strokeSharpness": "sharp",
      "boundElements": [],
      "lastCommittedPoint": null,
      "startArrowhead": null,
      "endArrowhead": null,
      "points": [
        [
          0,
          0
        ],
        [
          -0.18872764600492808,
          0
        ],
        [
          -0.18872764600492808,
          30.68702496034044
        ],
        [
          0,
          30.68702496034044
        ],
        [
          0,
          30.68702496034044
        ],
        [
          1.5290550528834126,
          30.613235116835554
        ],
        [
          3.024939236525432,
          30.39391099395009
        ],
        [
          4.479241693692304,
          30.032141862517065
        ],
        [
          5.883562146844901,
          29.53107341840757
        ],
        [
          7.22950384500898,
          28.893752613676078
        ],
        [
          8.508638298126394,
          28.12328282541513
        ],
        [
          9.712586388047287,
          27.222781536976786
        ],
        [
          10.832933730973021,
          26.195309806675052
        ],
        [
          11.881254512832816,
          25.03471730536289
        ],
        [
          12.789796369192741,
          23.796639120553813
        ],
        [
          13.558559300052785,
          22.492120453445384
        ],
        [
          14.18755741167247,
          21.13212186767805
        ],
        [
          14.676776597792285,
          19.727688564449355
        ],
        [
          15.026216858412209,
          18.289795213659296
        ],
        [
          15.235878193532269,
          16.829444697726853
        ],
        [
          15.305760603152454,
          15.357668111590055
        ],
        [
          15.235878193532269,
          13.885440125148886
        ],
        [
          15.026216858412209,
          12.423777727081868
        ],
        [
          14.676776597792285,
          10.983669693548487
        ],
        [
          14.18755741167247,
          9.576133013227258
        ],
        [
          13.558559300052785,
          8.212170568537182
        ],
        [
          12.789796369192741,
          6.902771135637755
        ],
        [
          11.881254512832816,
          5.658951703207488
        ],
        [
          10.832933730973021,
          4.491701047405876
        ],
        [
          9.700201092196151,
          3.4642434233636483
        ],
        [
          8.48740837756152,
          2.563742134925305
        ],
        [
          7.202962917738014,
          1.7932864529238728
        ],
        [
          5.855257937134992,
          1.1559515419328679
        ],
        [
          4.452707819551092,
          0.6548689915638524
        ],
        [
          3.0037093159605606,
          0.2931139663903432
        ],
        [
          1.516669757032278,
          0.0737898435048792
        ],
        [
          0,
          0
        ],
        [
          0,
          0
        ]
      ]
    },
    {
      "type": "line",
      "id": "0Eekj_HvYZNIvQ",
      "fillStyle": "solid",
      "strokeWidth": 1,
      "strokeStyle": "solid",
      "roughness": 0,
      "opacity": 100,
      "angle": 0,
      "x": 162.36598222501198,
      "y": 172.76077968022537,
      "strokeColor": "#000000",
      "backgroundColor": "#679df6",
      "width": 15.28689700762064,
      "height": 30.687010854080924,
      "seed": 1497166327,
      "groupIds": [
        "dw4no3UtBSH2QQ",
        "3f83HsVzb_Cvng",
        "5yNehOcTKdz-wg"
      ],
      "strokeSharpness": "sharp",
      "boundElements": [],
      "lastCommittedPoint": null,
      "startArrowhead": null,
      "endArrowhead": null,
      "points": [
        [
          0,
          0
        ],
        [
          0,
          30.687010854080924
        ],
        [
          0,
          30.687010854080924
        ],
        [
          1.5650189615080903,
          30.60117426495318
        ],
        [
          3.0843618547178067,
          30.36293364806274
        ],
        [
          4.550397193233403,
          29.980075658659963
        ],
        [
          5.955521703178158,
          29.460288208178653
        ],
        [
          7.292075685637307,
          28.81135795186915
        ],
        [
          8.552427654215101,
          28.04101511994381
        ],
        [
          9.728974335034815,
          27.156975836355432
        ],
        [
          10.814056029181694,
          26.167012650094893
        ],
        [
          11.800069462779012,
          25.078841685114988
        ],
        [
          12.679354936911992,
          23.900207277887567
        ],
        [
          13.444309177703923,
          22.638881977403468
        ],
        [
          14.087286592499543,
          21.302567801356016
        ],
        [
          14.600669801162626,
          19.899023192476548
        ],
        [
          14.97682731729742,
          18.435978380977403
        ],
        [
          15.20809944198916,
          16.921177703330404
        ],
        [
          15.28689700762064,
          15.362379602266905
        ],
        [
          15.20809944198916,
          13.803158313418058
        ],
        [
          14.97682731729742,
          12.287158603712584
        ],
        [
          14.600669801162626,
          10.822251765957905
        ],
        [
          14.087286592499543,
          9.416280880442459
        ],
        [
          13.444309177703923,
          8.077131346233184
        ],
        [
          12.679354936911992,
          6.812603924839975
        ],
        [
          11.800069462779012,
          5.630569909070264
        ],
        [
          10.814056029181694,
          4.5388723792124726
        ],
        [
          9.728974335034815,
          3.5453826280740413
        ],
        [
          8.552427654215101,
          2.6579578422028973
        ],
        [
          7.292075685637307,
          1.884412889368438
        ],
        [
          5.955521703178158,
          1.2326190623781015
        ],
        [
          4.550397193233403,
          0.710419441520307
        ],
        [
          3.0843618547178067,
          0.32568531960249486
        ],
        [
          1.5650189615080903,
          0.08627388317259437
        ],
        [
          0,
          0
        ],
        [
          0,
          0
        ]
      ]
    },
    {
      "type": "line",
      "id": "y7kInCBLrzUT3g",
      "fillStyle": "solid",
      "strokeWidth": 1,
      "strokeStyle": "solid",
      "roughness": 0,
      "opacity": 100,
      "angle": 0,
      "x": 162.3282338745596,
      "y": 172.76077968022537,
      "strokeColor": "#000000",
      "backgroundColor": "#aecbfa",
      "width": 15.400127952719792,
      "height": 30.724745098274298,
      "seed": 448564473,
      "groupIds": [
        "X-VTHlrm0ONY2w",
        "3f83HsVzb_Cvng",
        "5yNehOcTKdz-wg"
      ],
      "strokeSharpness": "sharp",
      "boundElements": [],
      "lastCommittedPoint": null,
      "startArrowhead": null,
      "endArrowhead": null,
      "points": [
        [
          0,
          0
        ],
        [
          0,
          0
        ],
        [
          -1.5658582839490265,
          0.07922075341682308
        ],
        [
          -3.0875992412757007,
          0.31176244146460247
        ],
        [
          -4.557372738561863,
          0.6899371527095473
        ],
        [
          -5.967307483000053,
          1.2060851882368904
        ],
        [
          -7.309581553691132,
          1.8524763178343056
        ],
        [
          -8.576316604697897,
          2.6214649488465374
        ],
        [
          -9.75966955573194,
          3.5053349573207724
        ],
        [
          -10.851811432764343,
          4.496412538082731
        ],
        [
          -11.844849783598406,
          5.587023885958134
        ],
        [
          -12.730969740464731,
          6.76948108951319
        ],
        [
          -13.502292957426123,
          8.036082131054597
        ],
        [
          -14.15098340732392,
          9.379153205408075
        ],
        [
          -14.669198009869703,
          10.790978188620814
        ],
        [
          -15.049065472256036,
          12.263939700556579
        ],
        [
          -15.282749767324248,
          13.79029340474353
        ],
        [
          -15.362379602266905,
          15.362379602266907
        ],
        [
          -15.283165901979839,
          16.934451693530768
        ],
        [
          -15.050617160802304,
          18.460805397717724
        ],
        [
          -14.672428343297847,
          19.93376690965349
        ],
        [
          -14.156294414030016,
          21.345620105385244
        ],
        [
          -13.509896231302845,
          22.688691179738726
        ],
        [
          -12.740921706550125,
          23.955278115020626
        ],
        [
          -11.857044644946134,
          25.13772121231617
        ],
        [
          -10.865952957924666,
          26.22833256019157
        ],
        [
          -9.775348663179019,
          27.219424247213038
        ],
        [
          -8.592898512753717,
          28.103308361946787
        ],
        [
          -7.326304524342065,
          28.87226878044
        ],
        [
          -5.983240503118339,
          29.51865991003741
        ],
        [
          -4.571380254256823,
          30.034807945564754
        ],
        [
          -3.098432848580572,
          30.412996763069206
        ],
        [
          -1.5720791443936193,
          30.64555255737651
        ],
        [
          0,
          30.724745098274298
        ],
        [
          0.037748350452886825,
          30.724745098274298
        ],
        [
          0.037748350452886825,
          0.03773424419337639
        ],
        [
          0.037748350452886825,
          0.03773424419337639
        ],
        [
          0,
          0
        ],
        [
          0,
          0
        ]
      ]
    },
    {
      "type": "line",
      "id": "XtzaJnPOmRflOw",
      "fillStyle": "solid",
      "strokeWidth": 1,
      "strokeStyle": "solid",
      "roughness": 0,
      "opacity": 100,
      "angle": 0,
      "x": 226.23122578794982,
      "y": 146.26348306992622,
      "strokeColor": "#000000",
      "backgroundColor": "#aecbfa",
      "width": 15.362379602266905,
      "height": 30.68703906659994,
      "seed": 1725537047,
      "groupIds": [
        "X-VTHlrm0ONY2w",
        "3f83HsVzb_Cvng",
        "5yNehOcTKdz-wg"
      ],
      "strokeSharpness": "sharp",
      "boundElements": [],
      "lastCommittedPoint": null,
      "startArrowhead": null,
      "endArrowhead": null,
      "points": [
        [
          0,
          0
        ],
        [
          0,
          0
        ],
        [
          -1.5290621060131748,
          0.07378984350487917
        ],
        [
          -3.0249462896551886,
          0.29311396639034293
        ],
        [
          -4.479245220257184,
          0.6548689915638521
        ],
        [
          -5.883565673409782,
          1.1559656481923783
        ],
        [
          -7.229500318444105,
          1.7932864529238726
        ],
        [
          -8.508641824691273,
          2.563742134925304
        ],
        [
          -9.71258286148241,
          3.464243423363647
        ],
        [
          -10.832930204408145,
          4.491701047405871
        ],
        [
          -11.86038782845037,
          5.624433686182741
        ],
        [
          -12.760903223148226,
          6.837233453947126
        ],
        [
          -13.531358905149657,
          8.12169302003014
        ],
        [
          -14.168679709881152,
          9.469390947503415
        ],
        [
          -14.669776366509678,
          10.871934011957551
        ],
        [
          -15.03153139168319,
          12.320928988983207
        ],
        [
          -15.250841408309139,
          13.807982654170997
        ],
        [
          -15.32463125181402,
          15.324645358073523
        ],
        [
          -15.250841408309139,
          16.842859750522315
        ],
        [
          -15.03153139168319,
          18.333665680740175
        ],
        [
          -14.669776366509678,
          19.787301617145125
        ],
        [
          -14.168679709881152,
          21.194048346933716
        ],
        [
          -13.531358905149657,
          22.544200763561985
        ],
        [
          -12.760903223148226,
          23.827969122928952
        ],
        [
          -11.86038782845037,
          25.035676531009656
        ],
        [
          -10.832930204408145,
          26.15757556248166
        ],
        [
          -9.700211671890786,
          27.185047292783402
        ],
        [
          -8.487411904126404,
          28.085548581221737
        ],
        [
          -7.2029523380433815,
          28.856018369482694
        ],
        [
          -5.855254410570113,
          29.493339174214192
        ],
        [
          -4.452711346115969,
          29.994407618323695
        ],
        [
          -3.00371636909032,
          30.356176749756713
        ],
        [
          -1.516662703902524,
          30.575500872642166
        ],
        [
          0,
          30.649290716147053
        ],
        [
          0.037748350452886825,
          30.649290716147053
        ],
        [
          0.037748350452886825,
          -0.03774835045288791
        ],
        [
          0.037748350452886825,
          -0.03774835045288791
        ],
        [
          0,
          0
        ],
        [
          0,
          0
        ]
      ]
    },
    {
      "type": "line",
      "id": "Pp5OY4qXvbbGBQ",
      "fillStyle": "solid",
      "strokeWidth": 1,
      "strokeStyle": "solid",
      "roughness": 0,
      "opacity": 100,
      "angle": 0,
      "x": 226.26897413840516,
      "y": 146.26348306992668,
      "strokeColor": "#000000",
      "backgroundColor": "#679df6",
      "width": 15.28689700762064,
      "height": 30.68702496034044,
      "seed": 1098024409,
      "groupIds": [
        "rNdTF0lMFV9UQQ",
        "3f83HsVzb_Cvng",
        "5yNehOcTKdz-wg"
      ],
      "strokeSharpness": "sharp",
      "boundElements": [],
      "lastCommittedPoint": null,
      "startArrowhead": null,
      "endArrowhead": null,
      "points": [
        [
          0,
          0
        ],
        [
          0,
          30.68702496034044
        ],
        [
          0,
          30.68702496034044
        ],
        [
          1.5165921726049647,
          30.61168342828928
        ],
        [
          3.0031239061908317,
          30.388607040373753
        ],
        [
          4.4507082572653305,
          30.022211055820957
        ],
        [
          5.8505429198932575,
          29.516924840117483
        ],
        [
          7.193755056841854,
          28.877163652490506
        ],
        [
          8.47148593713787,
          28.107370964686115
        ],
        [
          9.674919148586588,
          27.211947929671922
        ],
        [
          10.79518185395525,
          26.195338019194068
        ],
        [
          11.822653584256988,
          25.062591274157697
        ],
        [
          12.723154872695332,
          23.84980561265282
        ],
        [
          13.493624660956277,
          22.56536015282931
        ],
        [
          14.130945465687768,
          21.21764811909653
        ],
        [
          14.632013909797275,
          19.81509094838288
        ],
        [
          14.993783041230294,
          18.36609597135723
        ],
        [
          15.213107164115762,
          16.87907051868845
        ],
        [
          15.28689700762064,
          15.362393708526424
        ],
        [
          15.213107164115762,
          13.844165209818113
        ],
        [
          14.993783041230294,
          12.353373385859761
        ],
        [
          14.632013909797275,
          10.89973744945481
        ],
        [
          14.130945465687768,
          9.492976613406714
        ],
        [
          13.493624660956277,
          8.142852409297463
        ],
        [
          12.723154872695332,
          6.859055837411485
        ],
        [
          11.822653584256988,
          5.651348429330766
        ],
        [
          10.79518185395525,
          4.529449397858762
        ],
        [
          9.674919148586588,
          3.4895500529273544
        ],
        [
          8.47148593713787,
          2.579668101913837
        ],
        [
          7.193755056841854,
          1.8024978403849103
        ],
        [
          5.8505429198932575,
          1.1606771388692347
        ],
        [
          4.4507082572653305,
          0.6568579741549802
        ],
        [
          3.0031239061908317,
          0.2937205355493394
        ],
        [
          1.5165921726049647,
          0.07387448106194845
        ],
        [
          0,
          0
        ],
        [
          0,
          0
        ]
      ]
    },
    {
      "type": "line",
      "id": "RKd_J4xWpcPNxA",
      "fillStyle": "solid",
      "strokeWidth": 1,
      "strokeStyle": "solid",
      "roughness": 0,
      "opacity": 100,
      "angle": 0,
      "x": 252.16232535397398,
      "y": 82.32275691234167,
      "strokeColor": "#000000",
      "backgroundColor": "#aecbfa",
      "width": 15.626603949177609,
      "height": 30.72475920453381,
      "seed": 692330551,
      "groupIds": [
        "MUrJo3iz8kH0Ng",
        "3f83HsVzb_Cvng",
        "5yNehOcTKdz-wg"
      ],
      "strokeSharpness": "sharp",
      "boundElements": [],
      "lastCommittedPoint": null,
      "startArrowhead": null,
      "endArrowhead": null,
      "points": [
        [
          0,
          0
        ],
        [
          0,
          0
        ],
        [
          -1.5658653370787814,
          0.07921370028706733
        ],
        [
          -3.087592188145951,
          0.31176244146460247
        ],
        [
          -4.557379791691615,
          0.6899512589690588
        ],
        [
          -5.967314536129809,
          1.20608518823689
        ],
        [
          -7.30958155369113,
          1.8524833709640613
        ],
        [
          -8.576323657827654,
          2.621457895716782
        ],
        [
          -9.759669555731938,
          3.505327904191017
        ],
        [
          -10.851804379634586,
          4.496426644342242
        ],
        [
          -11.844856836728159,
          5.587030939087889
        ],
        [
          -12.73096974046473,
          6.769474036383433
        ],
        [
          -13.502300010555878,
          8.036068024795085
        ],
        [
          -14.150990460453675,
          9.379139099148563
        ],
        [
          -14.669198009869701,
          10.790999348010082
        ],
        [
          -15.049079578515546,
          12.26393970055658
        ],
        [
          -15.282749767324248,
          13.790300457873284
        ],
        [
          -15.362379602266904,
          15.362379602266905
        ],
        [
          -15.283158848850082,
          16.928244939345685
        ],
        [
          -15.050617160802302,
          18.449985896672366
        ],
        [
          -14.672428343297845,
          19.919745287699012
        ],
        [
          -14.156308520289526,
          21.329694138396718
        ],
        [
          -13.509903284432598,
          22.671961155958037
        ],
        [
          -12.740928759679878,
          23.938703260094556
        ],
        [
          -11.857044644946132,
          25.122063264258355
        ],
        [
          -10.865952957924662,
          26.21418398190149
        ],
        [
          -9.775355716308772,
          27.20723643899507
        ],
        [
          -8.592912619013225,
          28.093349342731628
        ],
        [
          -7.326311577471818,
          28.86467961282278
        ],
        [
          -5.98324050311834,
          29.51337006272058
        ],
        [
          -4.571387307386578,
          30.031577612136594
        ],
        [
          -3.09845400796984,
          30.41144507452293
        ],
        [
          -1.572086197523376,
          30.64512936959115
        ],
        [
          0,
          30.72475920453381
        ],
        [
          0.26422434691070507,
          30.72475920453381
        ],
        [
          0.26422434691070507,
          0.037748350452887915
        ],
        [
          0.26422434691070507,
          0.037748350452887915
        ],
        [
          0,
          0
        ],
        [
          0,
          0
        ]
      ]
    },
    {
      "type": "line",
      "id": "hiljjgN-uIQ2Sw",
      "fillStyle": "solid",
      "strokeWidth": 1,
      "strokeStyle": "solid",
      "roughness": 0,
      "opacity": 100,
      "angle": 0,
      "x": 267.5247190625007,
      "y": 97.6851365146083,
      "strokeColor": "#000000",
      "backgroundColor": "#679df6",
      "width": 15.060435117422335,
      "height": 30.687010854080924,
      "seed": 347497145,
      "groupIds": [
        "yC4PBHJydhHsjg",
        "3f83HsVzb_Cvng",
        "5yNehOcTKdz-wg"
      ],
      "strokeSharpness": "sharp",
      "boundElements": [],
      "lastCommittedPoint": null,
      "startArrowhead": null,
      "endArrowhead": null,
      "points": [
        [
          0,
          0
        ],
        [
          0,
          0
        ],
        [
          -0.07749978975641092,
          -1.5513358897818978
        ],
        [
          -0.30497733063955046,
          -3.058110105766829
        ],
        [
          -0.6750127301463369,
          -4.512909808581485
        ],
        [
          -1.1801437769951644,
          -5.908336265112054
        ],
        [
          -1.8128659411258958,
          -7.236969582855471
        ],
        [
          -2.565745223775945,
          -8.491382816178906
        ],
        [
          -3.4312770948851714,
          -9.664205444487582
        ],
        [
          -4.4020557682100225,
          -10.748003469018906
        ],
        [
          -5.470604926209371,
          -11.735371103529332
        ],
        [
          -6.629420038823081,
          -12.6189166680348
        ],
        [
          -7.871067107288568,
          -13.391192057513221
        ],
        [
          -9.188055707805209,
          -14.044826751369813
        ],
        [
          -10.572965947869921,
          -14.57239380397175
        ],
        [
          -12.018321509941599,
          -14.966494482205228
        ],
        [
          -13.516617863960091,
          -15.219715946696928
        ],
        [
          -15.060435117422335,
          -15.324631251814026
        ],
        [
          -15.060435117422335,
          15.362379602266898
        ],
        [
          -15.060435117422335,
          15.362379602266898
        ],
        [
          -13.522838724404682,
          15.250404114264288
        ],
        [
          -12.029141010986951,
          14.9902423700929
        ],
        [
          -10.586987569824394,
          14.589413006072416
        ],
        [
          -9.203995781053251,
          14.055448764782003
        ],
        [
          -7.88779713106926,
          13.395868282541286
        ],
        [
          -6.645994893749143,
          12.618176089410444
        ],
        [
          -5.486276980526693,
          11.729904927968608
        ],
        [
          -4.41621845275961,
          10.738573434535432
        ],
        [
          -3.443493115622166,
          9.651700245430586
        ],
        [
          -2.5757042429910886,
          8.476789890714205
        ],
        [
          -1.820469215002614,
          7.221389219224964
        ],
        [
          -1.1854477305715072,
          5.8930027610229985
        ],
        [
          -0.6782712760935006,
          4.499149152427961
        ],
        [
          -0.30654312544533013,
          3.047361136019031
        ],
        [
          -0.07792297754176403,
          1.5451291355968184
        ],
        [
          0,
          0
        ],
        [
          0,
          0
        ]
      ]
    },
    {
      "type": "line",
      "id": "ZvC0uhZCeiy3kQ",
      "fillStyle": "solid",
      "strokeWidth": 1,
      "strokeStyle": "solid",
      "roughness": 0,
      "opacity": 100,
      "angle": 0,
      "x": 236.83769410216223,
      "y": 44.803809504759556,
      "strokeColor": "#000000",
      "backgroundColor": "#679df6",
      "width": 15.192540237747938,
      "height": 30.68702496034044,
      "seed": 39911767,
      "groupIds": [
        "yC4PBHJydhHsjg",
        "3f83HsVzb_Cvng",
        "5yNehOcTKdz-wg"
      ],
      "strokeSharpness": "sharp",
      "boundElements": [],
      "lastCommittedPoint": null,
      "startArrowhead": null,
      "endArrowhead": null,
      "points": [
        [
          0,
          0
        ],
        [
          0,
          0
        ],
        [
          1.048320781859804,
          -1.1668274680162725
        ],
        [
          1.9568626382197216,
          -2.4095113465558597
        ],
        [
          2.725625569079769,
          -3.717225081443658
        ],
        [
          3.3546236806994543,
          -5.0791209591152935
        ],
        [
          3.843842866819264,
          -6.484358319136131
        ],
        [
          4.193283127439194,
          -7.922114133895967
        ],
        [
          4.402944462559251,
          -9.381540689830409
        ],
        [
          4.472826872179436,
          -10.851807906199472
        ],
        [
          4.402944462559251,
          -12.322075122568531
        ],
        [
          4.193283127439194,
          -13.781501678502966
        ],
        [
          3.843842866819264,
          -15.21925396669792
        ],
        [
          3.3546236806994543,
          -16.62449485328365
        ],
        [
          2.725625569079769,
          -17.98639073095528
        ],
        [
          1.9568626382197216,
          -19.294100939278202
        ],
        [
          1.048320781859804,
          -20.53678834438267
        ],
        [
          0,
          -21.703615812398937
        ],
        [
          -1.1185840604867892,
          -22.71868461402515
        ],
        [
          -2.317221143701584,
          -23.610348330879514
        ],
        [
          -3.587518025235017,
          -24.375500059304606
        ],
        [
          -4.921067374418206,
          -25.011057581597154
        ],
        [
          -6.309461860582273,
          -25.51391046753487
        ],
        [
          -7.744308259317849,
          -25.88096944628472
        ],
        [
          -9.217185133696546,
          -26.109138193883922
        ],
        [
          -10.719713365568502,
          -26.195316859804812
        ],
        [
          -10.719713365568502,
          4.491708100535632
        ],
        [
          -10.719713365568502,
          4.491708100535632
        ],
        [
          -9.217185133696546,
          4.4055188549201
        ],
        [
          -7.744308259317849,
          4.177357160450654
        ],
        [
          -6.309461860582273,
          3.810298181700812
        ],
        [
          -4.921067374418206,
          3.3074382426333493
        ],
        [
          -3.587518025235017,
          2.671894826600301
        ],
        [
          -2.317221143701584,
          1.9067289919157062
        ],
        [
          -1.1185840604867892,
          1.0150723281910814
        ],
        [
          0,
          0
        ],
        [
          0,
          0
        ]
      ]
    },
    {
      "type": "line",
      "id": "XxHGcfvEAaallA",
      "fillStyle": "solid",
      "strokeWidth": 1,
      "strokeStyle": "solid",
      "roughness": 0,
      "opacity": 100,
      "angle": 0,
      "x": 226.0047497914943,
      "y": 49.29551760529512,
      "strokeColor": "#000000",
      "backgroundColor": "#aecbfa",
      "width": 15.437862196913166,
      "height": 30.68702496034044,
      "seed": 288072601,
      "groupIds": [
        "KyqO4Yol-DYlog",
        "3f83HsVzb_Cvng",
        "5yNehOcTKdz-wg"
      ],
      "strokeSharpness": "sharp",
      "boundElements": [],
      "lastCommittedPoint": null,
      "startArrowhead": null,
      "endArrowhead": null,
      "points": [
        [
          0,
          0
        ],
        [
          0.11323094509915776,
          0
        ],
        [
          0.11323094509915776,
          -30.68702496034044
        ],
        [
          0,
          -30.68702496034044
        ],
        [
          0,
          -30.68702496034044
        ],
        [
          -1.5290479997536526,
          -30.61323159027068
        ],
        [
          -3.0249321833956717,
          -30.393910993950094
        ],
        [
          -4.479245220257177,
          -30.032159495341464
        ],
        [
          -5.883565673409774,
          -29.53107341840757
        ],
        [
          -7.229500318444101,
          -28.8937490871112
        ],
        [
          -8.508627718431756,
          -28.123286351980013
        ],
        [
          -9.712582861482403,
          -27.22277801041191
        ],
        [
          -10.832930204408136,
          -26.195323912934565
        ],
        [
          -11.849554221145496,
          -25.062591274157693
        ],
        [
          -12.744977256159684,
          -23.849798559523066
        ],
        [
          -13.514769943964074,
          -22.5653460465698
        ],
        [
          -14.154531131591062,
          -21.217648119096534
        ],
        [
          -14.659817347294519,
          -19.815094474947756
        ],
        [
          -15.026213331847325,
          -18.366099497922097
        ],
        [
          -15.249289719762858,
          -16.87905993899382
        ],
        [
          -15.324631251814008,
          -15.362390181961533
        ],
        [
          -15.250841408309128,
          -13.844165209818115
        ],
        [
          -15.031517285423662,
          -12.35336985929488
        ],
        [
          -14.669776366509668,
          -10.899730396325054
        ],
        [
          -14.168679709881141,
          -9.49297661340671
        ],
        [
          -13.531358905149647,
          -8.142838303037951
        ],
        [
          -12.760889116888706,
          -6.859048784281729
        ],
        [
          -11.860387828450362,
          -5.6513484293307705
        ],
        [
          -10.832930204408136,
          -4.529449397858762
        ],
        [
          -9.712582861482403,
          -3.489542999797596
        ],
        [
          -8.508627718431756,
          -2.579668101913839
        ],
        [
          -7.229500318444101,
          -1.8024907872551594
        ],
        [
          -5.883565673409774,
          -1.1606771388692358
        ],
        [
          -4.479245220257177,
          -0.6568579741549776
        ],
        [
          -3.0249321833956717,
          -0.2937134824195802
        ],
        [
          -1.5290479997536526,
          -0.07387448106194938
        ],
        [
          0,
          0
        ],
        [
          0,
          0
        ]
      ]
    },
    {
      "type": "line",
      "id": "Fw6Hmgujm4dMwA",
      "fillStyle": "solid",
      "strokeWidth": 1,
      "strokeStyle": "solid",
      "roughness": 0,
      "opacity": 100,
      "angle": 0,
      "x": 158.21398106603328,
      "y": 20.64674134742745,
      "strokeColor": "#000000",
      "backgroundColor": "#4385f4",
      "width": 8.15301596927553,
      "height": 15.928566066846566,
      "seed": 595902071,
      "groupIds": [
        "WMn6SHkFpmQX6A",
        "3f83HsVzb_Cvng",
        "5yNehOcTKdz-wg"
      ],
      "strokeSharpness": "sharp",
      "boundElements": [],
      "lastCommittedPoint": null,
      "startArrowhead": null,
      "endArrowhead": null,
      "points": [
        [
          0,
          0
        ],
        [
          8.15301596927553,
          0
        ],
        [
          8.15301596927553,
          15.928566066846566
        ],
        [
          0,
          15.928566066846566
        ],
        [
          0,
          0
        ]
      ]
    },
    {
      "type": "line",
      "id": "J6mqVNu6Aj62bw",
      "fillStyle": "solid",
      "strokeWidth": 1,
      "strokeStyle": "solid",
      "roughness": 0,
      "opacity": 100,
      "angle": 0,
      "x": 104.36976783505679,
      "y": 46.16755330242768,
      "strokeColor": "#000000",
      "backgroundColor": "#4385f4",
      "width": 17.028096097298135,
      "height": 17.028462860045444,
      "seed": 1392887929,
      "groupIds": [
        "WMn6SHkFpmQX6A",
        "3f83HsVzb_Cvng",
        "5yNehOcTKdz-wg"
      ],
      "strokeSharpness": "sharp",
      "boundElements": [],
      "lastCommittedPoint": null,
      "startArrowhead": null,
      "endArrowhead": null,
      "points": [
        [
          0,
          0
        ],
        [
          5.7648614996201495,
          -5.765235315497204
        ],
        [
          17.028096097298135,
          5.497992229051031
        ],
        [
          11.26324165080775,
          11.26322754454824
        ],
        [
          0,
          0
        ]
      ]
    },
    {
      "type": "line",
      "id": "354OYuzX7XiPvA",
      "fillStyle": "solid",
      "strokeWidth": 1,
      "strokeStyle": "solid",
      "roughness": 0,
      "opacity": 100,
      "angle": 0,
      "x": 84.33903449752279,
      "y": 102.29422985366932,
      "strokeColor": "#000000",
      "backgroundColor": "#4385f4",
      "width": 15.928566066846566,
      "height": 8.153001863016016,
      "seed": 527685527,
      "groupIds": [
        "WMn6SHkFpmQX6A",
        "3f83HsVzb_Cvng",
        "5yNehOcTKdz-wg"
      ],
      "strokeSharpness": "sharp",
      "boundElements": [],
      "lastCommittedPoint": null,
      "startArrowhead": null,
      "endArrowhead": null,
      "points": [
        [
          0,
          0
        ],
        [
          0,
          -8.153001863016016
        ],
        [
          15.928566066846566,
          -8.153001863016016
        ],
        [
          15.928566066846566,
          0
        ],
        [
          0,
          0
        ]
      ]
    },
    {
      "type": "line",
      "id": "EqsQH2Ey6HpnSw",
      "fillStyle": "solid",
      "strokeWidth": 1,
      "strokeStyle": "solid",
      "roughness": 0,
      "opacity": 100,
      "angle": 0,
      "x": 109.83946290752965,
      "y": 156.12033064743287,
      "strokeColor": "#000000",
      "backgroundColor": "#4385f4",
      "width": 17.028096097298135,
      "height": 17.028089044168386,
      "seed": 604524889,
      "groupIds": [
        "WMn6SHkFpmQX6A",
        "3f83HsVzb_Cvng",
        "5yNehOcTKdz-wg"
      ],
      "strokeSharpness": "sharp",
      "boundElements": [],
      "lastCommittedPoint": null,
      "startArrowhead": null,
      "endArrowhead": null,
      "points": [
        [
          0,
          0
        ],
        [
          -5.764861499620144,
          -5.764861499620146
        ],
        [
          5.49837309805784,
          -17.028089044168386
        ],
        [
          11.263234597677991,
          -11.262860781800931
        ],
        [
          0,
          0
        ]
      ]
    },
    {
      "type": "line",
      "id": "7EQWN2FaIE64dg",
      "fillStyle": "solid",
      "strokeWidth": 1,
      "strokeStyle": "solid",
      "roughness": 0,
      "opacity": 100,
      "angle": 0,
      "x": 165.9366996951701,
      "y": 176.17673737728046,
      "strokeColor": "#000000",
      "backgroundColor": "#4385f4",
      "width": 8.153008916145772,
      "height": 15.928576646541199,
      "seed": 1013107895,
      "groupIds": [
        "WMn6SHkFpmQX6A",
        "3f83HsVzb_Cvng",
        "5yNehOcTKdz-wg"
      ],
      "strokeSharpness": "sharp",
      "boundElements": [],
      "lastCommittedPoint": null,
      "startArrowhead": null,
      "endArrowhead": null,
      "points": [
        [
          0,
          0
        ],
        [
          -8.153008916145772,
          0
        ],
        [
          -8.153008916145772,
          -15.928576646541199
        ],
        [
          0,
          -15.928576646541199
        ],
        [
          0,
          0
        ]
      ]
    },
    {
      "type": "line",
      "id": "DSu02iD2n-nzlw",
      "fillStyle": "solid",
      "strokeWidth": 1,
      "strokeStyle": "solid",
      "roughness": 0,
      "opacity": 100,
      "angle": 0,
      "x": 219.7839316656823,
      "y": 150.65668010716308,
      "strokeColor": "#000000",
      "backgroundColor": "#4385f4",
      "width": 17.028469913175197,
      "height": 17.028074937908872,
      "seed": 1233567289,
      "groupIds": [
        "WMn6SHkFpmQX6A",
        "3f83HsVzb_Cvng",
        "5yNehOcTKdz-wg"
      ],
      "strokeSharpness": "sharp",
      "boundElements": [],
      "lastCommittedPoint": null,
      "startArrowhead": null,
      "endArrowhead": null,
      "points": [
        [
          0,
          0
        ],
        [
          -5.765242368626966,
          5.764847393360634
        ],
        [
          -17.028469913175197,
          -5.497999282180789
        ],
        [
          -11.26360841355505,
          -11.263227544548238
        ],
        [
          0,
          0
        ]
      ]
    },
    {
      "type": "line",
      "id": "0DlMloEwlqeu7w",
      "fillStyle": "solid",
      "strokeWidth": 1,
      "strokeStyle": "solid",
      "roughness": 0,
      "opacity": 100,
      "angle": 0,
      "x": 239.83126807066174,
      "y": 94.53376992721087,
      "strokeColor": "#000000",
      "backgroundColor": "#4385f4",
      "width": 15.928562540281687,
      "height": 8.153008916145772,
      "seed": 100015575,
      "groupIds": [
        "WMn6SHkFpmQX6A",
        "3f83HsVzb_Cvng",
        "5yNehOcTKdz-wg"
      ],
      "strokeSharpness": "sharp",
      "boundElements": [],
      "lastCommittedPoint": null,
      "startArrowhead": null,
      "endArrowhead": null,
      "points": [
        [
          0,
          0
        ],
        [
          0,
          8.153008916145772
        ],
        [
          -15.928562540281687,
          8.153008916145772
        ],
        [
          -15.928562540281687,
          0
        ],
        [
          0,
          0
        ]
      ]
    },
    {
      "type": "line",
      "id": "TCVrYsUqiFnPBA",
      "fillStyle": "solid",
      "strokeWidth": 1,
      "strokeStyle": "solid",
      "roughness": 0,
      "opacity": 100,
      "angle": 0,
      "x": 214.32858971226347,
      "y": 40.707302370699836,
      "strokeColor": "#000000",
      "backgroundColor": "#4385f4",
      "width": 17.028455806915687,
      "height": 17.028089044168386,
      "seed": 308580121,
      "groupIds": [
        "WMn6SHkFpmQX6A",
        "3f83HsVzb_Cvng",
        "5yNehOcTKdz-wg"
      ],
      "strokeSharpness": "sharp",
      "boundElements": [],
      "lastCommittedPoint": null,
      "startArrowhead": null,
      "endArrowhead": null,
      "points": [
        [
          0,
          0
        ],
        [
          5.76484739336064,
          5.765235315497207
        ],
        [
          -5.4983801511875985,
          17.028089044168386
        ],
        [
          -11.263608413555048,
          11.262853728671178
        ],
        [
          0,
          0
        ]
      ]
    },
    {
      "type": "ellipse",
      "id": "y2CIVQgUqW6mqw",
      "fillStyle": "solid",
      "strokeWidth": 1,
      "strokeStyle": "solid",
      "roughness": 0,
      "opacity": 100,
      "angle": 0,
      "x": 154.21296625573814,
      "y": 0,
      "strokeColor": "#000000",
      "backgroundColor": "#fff",
      "width": 15.626602185895168,
      "height": 15.626602185895168,
      "seed": 524438263,
      "groupIds": [
        "hS0xlSwM65EemA",
        "3f83HsVzb_Cvng",
        "5yNehOcTKdz-wg"
      ],
      "strokeSharpness": "sharp",
      "boundElements": []
    },
    {
      "type": "ellipse",
      "id": "o9zr8O-2Kn_74g",
      "fillStyle": "solid",
      "strokeWidth": 1,
      "strokeStyle": "solid",
      "roughness": 0,
      "opacity": 100,
      "angle": 0,
      "x": 90.4987090414811,
      "y": 26.76150156110134,
      "strokeColor": "#000000",
      "backgroundColor": "#fff",
      "width": 15.626602185895168,
      "height": 15.626602185895168,
      "seed": 622150649,
      "groupIds": [
        "hS0xlSwM65EemA",
        "3f83HsVzb_Cvng",
        "5yNehOcTKdz-wg"
      ],
      "strokeSharpness": "sharp",
      "boundElements": []
    },
    {
      "type": "ellipse",
      "id": "ttg4j-CAkg-mUg",
      "fillStyle": "solid",
      "strokeWidth": 1,
      "strokeStyle": "solid",
      "roughness": 0,
      "opacity": 100,
      "angle": 0,
      "x": 64.07691794850007,
      "y": 90.13605183380082,
      "strokeColor": "#000000",
      "backgroundColor": "#fff",
      "width": 15.626602185895168,
      "height": 15.626602185895168,
      "seed": 1422644247,
      "groupIds": [
        "hS0xlSwM65EemA",
        "3f83HsVzb_Cvng",
        "5yNehOcTKdz-wg"
      ],
      "strokeSharpness": "sharp",
      "boundElements": []
    },
    {
      "type": "ellipse",
      "id": "e3BNbt7A9ChWxQ",
      "fillStyle": "solid",
      "strokeWidth": 1,
      "strokeStyle": "solid",
      "roughness": 0,
      "opacity": 100,
      "angle": 0,
      "x": 90.83841950960323,
      "y": 153.85032315431658,
      "strokeColor": "#000000",
      "backgroundColor": "#fff",
      "width": 15.626602185895168,
      "height": 15.626602185895168,
      "seed": 228351193,
      "groupIds": [
        "hS0xlSwM65EemA",
        "3f83HsVzb_Cvng",
        "5yNehOcTKdz-wg"
      ],
      "strokeSharpness": "sharp",
      "boundElements": []
    },
    {
      "type": "ellipse",
      "id": "DUJ_27EEWvyhDg",
      "fillStyle": "solid",
      "strokeWidth": 1,
      "strokeStyle": "solid",
      "roughness": 0,
      "opacity": 100,
      "angle": 0,
      "x": 154.51493895310114,
      "y": 180.27209485119033,
      "strokeColor": "#000000",
      "backgroundColor": "#fff",
      "width": 15.626602185895168,
      "height": 15.626602185895168,
      "seed": 1854355767,
      "groupIds": [
        "hS0xlSwM65EemA",
        "3f83HsVzb_Cvng",
        "5yNehOcTKdz-wg"
      ],
      "strokeSharpness": "sharp",
      "boundElements": []
    },
    {
      "type": "ellipse",
      "id": "9OJrNfDtlpeIuA",
      "fillStyle": "solid",
      "strokeWidth": 1,
      "strokeStyle": "solid",
      "roughness": 0,
      "opacity": 100,
      "angle": 0,
      "x": 218.41792381336336,
      "y": 153.77482645341138,
      "strokeColor": "#000000",
      "backgroundColor": "#fff",
      "width": 15.626602185895168,
      "height": 15.626602185895168,
      "seed": 193812921,
      "groupIds": [
        "hS0xlSwM65EemA",
        "3f83HsVzb_Cvng",
        "5yNehOcTKdz-wg"
      ],
      "strokeSharpness": "sharp",
      "boundElements": []
    },
    {
      "type": "ellipse",
      "id": "MjMejAZWRM6WVg",
      "fillStyle": "solid",
      "strokeWidth": 1,
      "strokeStyle": "solid",
      "roughness": 0,
      "opacity": 100,
      "angle": 0,
      "x": 244.34902337938593,
      "y": 89.87184159314938,
      "strokeColor": "#000000",
      "backgroundColor": "#fff",
      "width": 15.626602185895168,
      "height": 15.626602185895168,
      "seed": 1104738903,
      "groupIds": [
        "hS0xlSwM65EemA",
        "3f83HsVzb_Cvng",
        "5yNehOcTKdz-wg"
      ],
      "strokeSharpness": "sharp",
      "boundElements": []
    },
    {
      "type": "ellipse",
      "id": "Z2-OLVldUo3jLg",
      "fillStyle": "solid",
      "strokeWidth": 1,
      "strokeStyle": "solid",
      "roughness": 0,
      "opacity": 100,
      "angle": 0,
      "x": 218.1914478169051,
      "y": 26.15757379919978,
      "strokeColor": "#000000",
      "backgroundColor": "#fff",
      "width": 15.626602185895168,
      "height": 15.626602185895168,
      "seed": 537639577,
      "groupIds": [
        "hS0xlSwM65EemA",
        "3f83HsVzb_Cvng",
        "5yNehOcTKdz-wg"
      ],
      "strokeSharpness": "sharp",
      "boundElements": []
    },
    {
      "type": "ellipse",
      "id": "7Fx-ONQX5bDvqQ",
      "fillStyle": "solid",
      "strokeWidth": 1,
      "strokeStyle": "solid",
      "roughness": 0,
      "opacity": 100,
      "angle": 0,
      "x": 98.04779372228768,
      "y": 33.81989647823525,
      "strokeColor": "#000000",
      "backgroundColor": "#679df6",
      "width": 128.0324598232402,
      "height": 128.0324598232402,
      "seed": 60135287,
      "groupIds": [
        "3f83HsVzb_Cvng",
        "5yNehOcTKdz-wg"
      ],
      "strokeSharpness": "sharp",
      "boundElements": []
    },
    {
      "type": "ellipse",
      "id": "7lzPPHjp2l-PBg",
      "fillStyle": "solid",
      "strokeWidth": 1,
      "strokeStyle": "solid",
      "roughness": 0,
      "opacity": 100,
      "angle": 0,
      "x": 106.54050957999152,
      "y": 42.31261586250298,
      "strokeColor": "#000000",
      "backgroundColor": "#fff",
      "width": 111.047021054705,
      "height": 111.047021054705,
      "seed": 1540030329,
      "groupIds": [
        "3f83HsVzb_Cvng",
        "5yNehOcTKdz-wg"
      ],
      "strokeSharpness": "sharp",
      "boundElements": []
    },
    {
      "type": "line",
      "id": "yr1nNE9mXXdrDQ",
      "fillStyle": "solid",
      "strokeWidth": 1,
      "strokeStyle": "solid",
      "roughness": 0,
      "opacity": 100,
      "angle": 0,
      "x": 162.06402363390862,
      "y": 54.99507417650739,
      "strokeColor": "#000000",
      "backgroundColor": "#679df6",
      "width": 42.99204208859463,
      "height": 85.71983867088926,
      "seed": 1510051991,
      "groupIds": [
        "rndpaGFiZCaHTg",
        "3f83HsVzb_Cvng",
        "5yNehOcTKdz-wg"
      ],
      "strokeSharpness": "sharp",
      "boundElements": [],
      "lastCommittedPoint": null,
      "startArrowhead": null,
      "endArrowhead": null,
      "points": [
        [
          0,
          0
        ],
        [
          -0.11324505135866378,
          0
        ],
        [
          -0.11324505135866378,
          85.71983867088926
        ],
        [
          0,
          85.71983867088926
        ],
        [
          0,
          85.71983867088926
        ],
        [
          2.205217443179939,
          85.66410483955914
        ],
        [
          4.38164401069682,
          85.49870894678632
        ],
        [
          6.526557194464913,
          85.22633118187795
        ],
        [
          8.637276805177027,
          84.84963762788169
        ],
        [
          10.711094441006948,
          84.37130847410482
        ],
        [
          12.745301700128458,
          83.79403801611396
        ],
        [
          14.737176074455828,
          83.12053465573536
        ],
        [
          16.68406558720089,
          82.35342215723816
        ],
        [
          18.583219517758888,
          81.49542302870809
        ],
        [
          20.43195767682264,
          80.54918924693335
        ],
        [
          22.22757166256591,
          79.51742921374007
        ],
        [
          23.96738128568153,
          78.40283722469506
        ],
        [
          25.64864993182423,
          77.20805115032691
        ],
        [
          27.268683305427345,
          75.93577939246187
        ],
        [
          28.824801217183655,
          74.58868803414761
        ],
        [
          30.314281159007443,
          73.16948547721032
        ],
        [
          31.73442883533199,
          71.68083780469773
        ],
        [
          33.08253584433108,
          70.12541109965748
        ],
        [
          34.35590789043805,
          68.50591376391581
        ],
        [
          35.55183657182661,
          66.82501188052039
        ],
        [
          36.66759938041109,
          65.08538563877843
        ],
        [
          37.700544339403315,
          63.289743440516126
        ],
        [
          38.647920728198514,
          61.44072315626218
        ],
        [
          39.507062463749016,
          59.54103318784273
        ],
        [
          40.27523293170957,
          57.59335372456502
        ],
        [
          40.94976604903252,
          55.60035084947673
        ],
        [
          41.52792520137259,
          53.56474707066358
        ],
        [
          42.00703019942264,
          51.489166152394716
        ],
        [
          42.38437264135641,
          49.376330602755864
        ],
        [
          42.65724412534768,
          47.22890650479472
        ],
        [
          42.822950355829775,
          45.04958815407799
        ],
        [
          42.87879703723597,
          42.84105573991282
        ],
        [
          42.822950355829775,
          40.632607963304736
        ],
        [
          42.65724412534768,
          38.453607003427
        ],
        [
          42.38437264135641,
          36.30668367767851
        ],
        [
          42.00703019942264,
          34.19453933475573
        ],
        [
          41.52792520137259,
          32.11983300457659
        ],
        [
          40.94976604903252,
          30.085209610799488
        ],
        [
          40.27523293170957,
          28.09337050212091
        ],
        [
          39.507062463749016,
          26.146953549069476
        ],
        [
          38.647920728198514,
          24.248645994082175
        ],
        [
          37.700544339403315,
          22.40111392020666
        ],
        [
          36.66759938041109,
          20.607009304231116
        ],
        [
          35.55183657182661,
          18.869019388592495
        ],
        [
          34.35590789043805,
          17.18980320320871
        ],
        [
          33.08253584433108,
          15.572026831127445
        ],
        [
          31.73442883533199,
          14.018363408526152
        ],
        [
          30.314281159007443,
          12.531471965322739
        ],
        [
          28.824801217183655,
          11.114032690824407
        ],
        [
          27.268683305427345,
          9.768711668078835
        ],
        [
          25.64864993182423,
          8.498160873874195
        ],
        [
          23.96738128568153,
          7.305060497517681
        ],
        [
          22.22757166256591,
          6.192083675186727
        ],
        [
          20.43195767682264,
          5.161882383669506
        ],
        [
          18.583219517758888,
          4.217143865402964
        ],
        [
          16.68406558720089,
          3.360520097175275
        ],
        [
          14.737176074455828,
          2.5946842151638734
        ],
        [
          12.745301700128458,
          1.9223023024164407
        ],
        [
          10.711094441006948,
          1.346047495110415
        ],
        [
          8.637276805177027,
          0.8685858762934782
        ],
        [
          6.526557194464913,
          0.4925764758835551
        ],
        [
          4.38164401069682,
          0.2206994831878393
        ],
        [
          2.205217443179939,
          0.055613928124256584
        ],
        [
          0,
          0
        ],
        [
          0,
          0
        ]
      ]
    },
    {
      "type": "line",
      "id": "bDYcoxh1SDIcDw",
      "fillStyle": "solid",
      "strokeWidth": 1,
      "strokeStyle": "solid",
      "roughness": 0,
      "opacity": 100,
      "angle": 0,
      "x": 119.22297494712438,
      "y": 97.8361299164203,
      "strokeColor": "#000000",
      "backgroundColor": "#aecbfa",
      "width": 42.765551985877295,
      "height": 85.71983867088926,
      "seed": 1829677145,
      "groupIds": [
        "yXF_bMSGTwWSow",
        "3f83HsVzb_Cvng",
        "5yNehOcTKdz-wg"
      ],
      "strokeSharpness": "sharp",
      "boundElements": [],
      "lastCommittedPoint": null,
      "startArrowhead": null,
      "endArrowhead": null,
      "points": [
        [
          0,
          0
        ],
        [
          0,
          0
        ],
        [
          0.0556139281242566,
          2.201676772042532
        ],
        [
          0.22067832379857202,
          4.374576774681529
        ],
        [
          0.49251299771575324,
          6.516033924869291
        ],
        [
          0.8684377605686069,
          8.623339820779591
        ],
        [
          1.3457653699201846,
          10.693828379364803
        ],
        [
          1.9218015302037805,
          12.724805305058169
        ],
        [
          2.5938872115014715,
          14.713590408552491
        ],
        [
          3.3593422245060616,
          16.657503500540642
        ],
        [
          4.215465220521091,
          18.553878497974836
        ],
        [
          5.159583063369124,
          20.400021105288488
        ],
        [
          6.1890155637429665,
          22.1932511331743
        ],
        [
          7.301075479205669,
          23.930874286065617
        ],
        [
          8.493096726709553,
          25.610224480914752
        ],
        [
          9.76238501068791,
          27.228621528414536
        ],
        [
          11.106260141833548,
          28.783385239257726
        ],
        [
          12.522034877709519,
          30.271807211618167
        ],
        [
          14.007043135268137,
          31.691235468707603
        ],
        [
          15.558590618942707,
          33.03898982121892
        ],
        [
          17.174004192555785,
          34.31236186732585
        ],
        [
          18.850589560540666,
          35.50869963024027
        ],
        [
          20.585673586719913,
          36.625294708135954
        ],
        [
          22.376576081786336,
          37.65948101796516
        ],
        [
          24.220616856432734,
          38.6085783704208
        ],
        [
          26.11510866822217,
          39.46989246993604
        ],
        [
          28.057371327847438,
          40.24077133972287
        ],
        [
          30.044717592871613,
          40.91849247169539
        ],
        [
          32.07448138024698,
          41.50038978280605
        ],
        [
          34.143968394406855,
          41.98379719000707
        ],
        [
          36.250505499173805,
          42.366020397731845
        ],
        [
          38.39139839898111,
          42.64439332293264
        ],
        [
          40.56397395765133,
          42.816193457523724
        ],
        [
          42.765551985877295,
          42.87878293097641
        ],
        [
          42.765551985877295,
          -42.841055739912846
        ],
        [
          42.765551985877295,
          -42.841055739912846
        ],
        [
          40.56397395765133,
          -42.78190114065119
        ],
        [
          38.39139839898111,
          -42.613303126969235
        ],
        [
          36.250505499173805,
          -42.33795599443368
        ],
        [
          34.143968394406855,
          -41.95853993235172
        ],
        [
          32.07448138024698,
          -41.477749236290066
        ],
        [
          30.044717592871613,
          -40.89826409555589
        ],
        [
          28.057371327847438,
          -40.222785858845675
        ],
        [
          26.11510866822217,
          -39.454001768596356
        ],
        [
          24.220616856432734,
          -38.59458496098539
        ],
        [
          22.376576081786336,
          -37.64723678470921
        ],
        [
          20.585673586719913,
          -36.61465153533454
        ],
        [
          18.850589560540666,
          -35.499502349038806
        ],
        [
          17.174004192555785,
          -34.304490574518475
        ],
        [
          15.558590618942707,
          -33.032289347950986
        ],
        [
          14.007043135268137,
          -31.68560707116255
        ],
        [
          12.522034877709519,
          -30.267116880330605
        ],
        [
          11.106260141833548,
          -28.779513071021867
        ],
        [
          9.76238501068791,
          -27.22548993880302
        ],
        [
          8.493096726709553,
          -25.60772061985152
        ],
        [
          7.301075479205669,
          -23.928906462863814
        ],
        [
          6.1890155637429665,
          -22.191734710276858
        ],
        [
          5.159583063369124,
          -20.398885551397846
        ],
        [
          4.215465220521091,
          -18.553060334923224
        ],
        [
          3.3593422245060616,
          -16.656946303289978
        ],
        [
          2.5938872115014715,
          -14.713216592675494
        ],
        [
          1.9218015302037805,
          -12.72457255177627
        ],
        [
          1.3457653699201846,
          -10.693701423029239
        ],
        [
          0.8684377605686069,
          -8.623290448871359
        ],
        [
          0.49251299771575324,
          -6.516019818609806
        ],
        [
          0.22067832379857202,
          -4.374590880941071
        ],
        [
          0.0556139281242566,
          -2.2016979314318235
        ],
        [
          0,
          0
        ],
        [
          0,
          0
        ]
      ]
    },
    {
      "type": "line",
      "id": "WFsDn-a95v-tTw",
      "fillStyle": "solid",
      "strokeWidth": 1,
      "strokeStyle": "solid",
      "roughness": 0,
      "opacity": 100,
      "angle": 0,
      "x": 139.49225923925997,
      "y": 79.56733187004443,
      "strokeColor": "#000000",
      "backgroundColor": "#fff",
      "width": 22.458519343288877,
      "height": 8.605960909061404,
      "seed": 785474999,
      "groupIds": [
        "PnVPuVgivg_jHg",
        "3f83HsVzb_Cvng",
        "5yNehOcTKdz-wg"
      ],
      "strokeSharpness": "sharp",
      "boundElements": [],
      "lastCommittedPoint": null,
      "startArrowhead": null,
      "endArrowhead": null,
      "points": [
        [
          0,
          0
        ],
        [
          22.458519343288877,
          0
        ],
        [
          22.458519343288877,
          8.605960909061404
        ],
        [
          0,
          8.605960909061404
        ],
        [
          0,
          0
        ]
      ]
    },
    {
      "type": "line",
      "id": "56sEpIF64OhzKA",
      "fillStyle": "solid",
      "strokeWidth": 1,
      "strokeStyle": "solid",
      "roughness": 0,
      "opacity": 100,
      "angle": 0,
      "x": 161.9885269330025,
      "y": 79.56733187004443,
      "strokeColor": "#000000",
      "backgroundColor": "#aecbfa",
      "width": 23.062450631756555,
      "height": 8.605960909061404,
      "seed": 1839871289,
      "groupIds": [
        "vhA93QVZrQMaYg",
        "3f83HsVzb_Cvng",
        "5yNehOcTKdz-wg"
      ],
      "strokeSharpness": "sharp",
      "boundElements": [],
      "lastCommittedPoint": null,
      "startArrowhead": null,
      "endArrowhead": null,
      "points": [
        [
          0,
          0
        ],
        [
          23.062450631756555,
          0
        ],
        [
          23.062450631756555,
          8.605960909061404
        ],
        [
          0,
          8.605960909061404
        ],
        [
          0,
          0
        ]
      ]
    },
    {
      "type": "line",
      "id": "KfdN-grr54uzaw",
      "fillStyle": "solid",
      "strokeWidth": 1,
      "strokeStyle": "solid",
      "roughness": 0,
      "opacity": 100,
      "angle": 0,
      "x": 139.49225923925997,
      "y": 94.3635426405558,
      "strokeColor": "#000000",
      "backgroundColor": "#fff",
      "width": 22.458519343288877,
      "height": 8.60595385593165,
      "seed": 1093244631,
      "groupIds": [
        "WgWuMRxupcOhEg",
        "3f83HsVzb_Cvng",
        "5yNehOcTKdz-wg"
      ],
      "strokeSharpness": "sharp",
      "boundElements": [],
      "lastCommittedPoint": null,
      "startArrowhead": null,
      "endArrowhead": null,
      "points": [
        [
          0,
          0
        ],
        [
          22.458519343288877,
          0
        ],
        [
          22.458519343288877,
          8.60595385593165
        ],
        [
          0,
          8.60595385593165
        ],
        [
          0,
          0
        ]
      ]
    },
    {
      "type": "line",
      "id": "tX7gwTbleAduJQ",
      "fillStyle": "solid",
      "strokeWidth": 1,
      "strokeStyle": "solid",
      "roughness": 0,
      "opacity": 100,
      "angle": 0,
      "x": 161.9885269330025,
      "y": 94.3635426405558,
      "strokeColor": "#000000",
      "backgroundColor": "#aecbfa",
      "width": 23.062450631756555,
      "height": 8.60595385593165,
      "seed": 1895900697,
      "groupIds": [
        "CreHv-k1-_7cWA",
        "3f83HsVzb_Cvng",
        "5yNehOcTKdz-wg"
      ],
      "strokeSharpness": "sharp",
      "boundElements": [],
      "lastCommittedPoint": null,
      "startArrowhead": null,
      "endArrowhead": null,
      "points": [
        [
          0,
          0
        ],
        [
          23.062450631756555,
          0
        ],
        [
          23.062450631756555,
          8.60595385593165
        ],
        [
          0,
          8.60595385593165
        ],
        [
          0,
          0
        ]
      ]
    },
    {
      "type": "line",
      "id": "R0ejmVXcLkGThw",
      "fillStyle": "solid",
      "strokeWidth": 1,
      "strokeStyle": "solid",
      "roughness": 0,
      "opacity": 100,
      "angle": 0,
      "x": 139.49225923925997,
      "y": 109.15974635793737,
      "strokeColor": "#000000",
      "backgroundColor": "#fff",
      "width": 22.458519343288877,
      "height": 8.605946802801892,
      "seed": 2006885367,
      "groupIds": [
        "8xmOeivYqQtNwA",
        "3f83HsVzb_Cvng",
        "5yNehOcTKdz-wg"
      ],
      "strokeSharpness": "sharp",
      "boundElements": [],
      "lastCommittedPoint": null,
      "startArrowhead": null,
      "endArrowhead": null,
      "points": [
        [
          0,
          0
        ],
        [
          22.458519343288877,
          0
        ],
        [
          22.458519343288877,
          8.605946802801892
        ],
        [
          0,
          8.605946802801892
        ],
        [
          0,
          0
        ]
      ]
    },
    {
      "type": "line",
      "id": "jQQErNFf0N27Eg",
      "fillStyle": "solid",
      "strokeWidth": 1,
      "strokeStyle": "solid",
      "roughness": 0,
      "opacity": 100,
      "angle": 0,
      "x": 161.9885269330025,
      "y": 109.15974635793737,
      "strokeColor": "#000000",
      "backgroundColor": "#aecbfa",
      "width": 23.062450631756555,
      "height": 8.605946802801892,
      "seed": 1376189177,
      "groupIds": [
        "u89UHhQjRrAPSQ",
        "3f83HsVzb_Cvng",
        "5yNehOcTKdz-wg"
      ],
      "strokeSharpness": "sharp",
      "boundElements": [],
      "lastCommittedPoint": null,
      "startArrowhead": null,
      "endArrowhead": null,
      "points": [
        [
          0,
          0
        ],
        [
          23.062450631756555,
          0
        ],
        [
          23.062450631756555,
          8.605946802801892
        ],
        [
          0,
          8.605946802801892
        ],
        [
          0,
          0
        ]
      ]
    },
    {
      "type": "text",
      "id": "OetbXXDYIqZg8A",
      "fillStyle": "hachure",
      "strokeWidth": 2,
      "strokeStyle": "solid",
      "roughness": 0,
      "opacity": 100,
      "angle": 0,
      "x": 0,
      "y": 213.89940037147971,
      "strokeColor": "#000000",
      "backgroundColor": "transparent",
      "width": 319,
      "height": 78,
      "seed": 1916079383,
      "groupIds": [
        "MaV6n6y2ZopODw",
        "Zu5imhp21TKMlg",
        "Rzdlns-P93wPQg",
        "wzi0WrPthjOT9w",
        "rTLJtMLssLGxWA",
        "Suruju91L4VGxQ",
        "72qRd8Xnrlnfvg",
        "5yNehOcTKdz-wg"
      ],
      "strokeSharpness": "round",
      "boundElements": [],
      "fontSize": 33.94285714285716,
      "fontFamily": 2,
      "text": "Network Connectivity\nCenter",
      "rawText": "Network Connectivity\nCenter",
      "baseline": 70,
      "textAlign": "center",
      "verticalAlign": "top",
      "containerId": null,
      "originalText": "Network Connectivity\nCenter"
    }
  ]
}